{
  "db_path": "watcher.db",
  "logging": {
    "path": "logs/announce_watcher.log",
    "level": "INFO",
    "max_bytes": 1048576,
    "backup_count": 3
  },
  "notifier": {
    "type": "windows_toast",
    "enabled": true
  },
  "startup": {
    "enabled": false,
    "use_pythonw": true
  },
  "sites": [
    {
      "name": "kdual-board-1",
      "interval_seconds": 300,
      "enabled": true,
      "login_mode": "browser",
      "notify_on_first_run": false,
      "adapter_type": "playwright_login_board",
      "settings": {
        "start_url": "https://kpu.kdual.net/BBS/Board/List/S71855C704064",
        "login_url": "https://kpu.kdual.net/login",
        "username": "3154816",
        "password": "your-password",
        "username_selector": "input[type=\"text\"]",
        "password_selector": "input[type=\"password\"]",
        "submit_selector": "button:has-text(\"로그인\"), input[type=\"submit\"], a:has-text(\"로그인\")",
        "headless": false,
        "board_url": "https://kpu.kdual.net/BBS/Board/List/S71855C704064",
        "timeout_seconds": 20,
        "login_timeout_seconds": 20,
        "retries": 2,
        "retry_backoff_seconds": 2
      }
    },
    {
      "name": "kdual-board-2",
      "interval_seconds": 300,
      "enabled": true,
      "login_mode": "browser",
      "notify_on_first_run": false,
      "adapter_type": "playwright_login_board",
      "settings": {
        "start_url": "https://kpu.kdual.net/BBS/Board/List/S71954C705054",
        "login_url": "https://kpu.kdual.net/login",
        "username": "2026531039",
        "password": "3154816",
        "username_selector": "input[type=\"text\"]",
        "password_selector": "input[type=\"password\"]",
        "submit_selector": "button:has-text(\"로그인\"), input[type=\"submit\"], a:has-text(\"로그인\")",
        "headless": false,
        "board_url": "https://kpu.kdual.net/BBS/Board/List/S71954C705054",
        "timeout_seconds": 20,
        "login_timeout_seconds": 20,
        "retries": 2,
        "retry_backoff_seconds": 2
      }
    },
    {
      "name": "contract-board-2792",
      "interval_seconds": 300,
      "enabled": true,
      "login_mode": "none",
      "notify_on_first_run": false,
      "adapter_type": "tukorea_board",
      "settings": {
        "board_url": "https://contract.tukorea.ac.kr/contract/2792/subview.do",
        "timeout_seconds": 20,
        "retries": 2,
        "retry_backoff_seconds": 2
      }
    },
    {
      "name": "contract-board-3844",
      "interval_seconds": 300,
      "enabled": true,
      "login_mode": "none",
      "notify_on_first_run": false,
      "adapter_type": "tukorea_board",
      "settings": {
        "board_url": "https://contract.tukorea.ac.kr/contract/3844/subview.do",
        "timeout_seconds": 20,
        "retries": 2,
        "retry_backoff_seconds": 2
      }
    },
    {
      "name": "eclass-course-1",
      "interval_seconds": 300,
      "enabled": true,
      "login_mode": "browser",
      "notify_on_first_run": false,
      "adapter_type": "playwright_login_board",
      "settings": {
        "start_url": "https://eclass.tukorea.ac.kr/ilos/main/main_form.acl",
        "login_url": "https://eclass.tukorea.ac.kr/ilos/main/member/login_form.acl",
        "login_button_selector": "a[href=\"/ilos/main/member/login_form.acl\"]",
        "username": "3026531039",
        "password": "3154816",
        "username_selector": "input[name=\"usr_id\"], input[type=\"text\"]",
        "password_selector": "input[name=\"usr_pwd\"], input[type=\"password\"]",
        "submit_selector": "button:has-text(\"로그인\"), input[type=\"submit\"], a:has-text(\"로그인\")",
        "subject_change_selector": "#eclass_subject_change",
        "subject_popup_selector": "#subject_room",
        "current_course_selector": "#subject-span",
        "course_item_selector": ".roomGo",
        "course_name": "데이터구조와 알고리즘(01)",
        "headless": false,
        "board_url": "https://eclass.tukorea.ac.kr/ilos/st/course/notice_list_form.acl",
        "timeout_seconds": 20,
        "login_timeout_seconds": 20,
        "retries": 2,
        "retry_backoff_seconds": 2
      }
    },
    {
      "name": "eclass-zoom-1",
      "interval_seconds": 300,
      "enabled": true,
      "login_mode": "browser",
      "notify_on_first_run": false,
      "adapter_type": "playwright_login_board",
      "settings": {
        "start_url": "https://eclass.tukorea.ac.kr/ilos/main/main_form.acl",
        "login_url": "https://eclass.tukorea.ac.kr/ilos/main/member/login_form.acl",
        "login_button_selector": "a[href=\"/ilos/main/member/login_form.acl\"]",
        "username": "3026531039",
        "password": "3154816",
        "username_selector": "input[name=\"usr_id\"], input[type=\"text\"]",
        "password_selector": "input[name=\"usr_pwd\"], input[type=\"password\"]",
        "submit_selector": "button:has-text(\"로그인\"), input[type=\"submit\"], a:has-text(\"로그인\")",
        "subject_change_selector": "#eclass_subject_change",
        "subject_popup_selector": "#subject_room",
        "current_course_selector": "#subject-span",
        "course_item_selector": ".roomGo",
        "course_name": "인공지능기초실습(01)",
        "headless": false,
        "board_url": "https://eclass.tukorea.ac.kr/ilos/st/course/zoom_list_form.acl",
        "timeout_seconds": 20,
        "login_timeout_seconds": 20,
        "retries": 2,
        "retry_backoff_seconds": 2
      }
    },
    {
      "name": "eclass-course-2",
      "interval_seconds": 300,
      "enabled": true,
      "login_mode": "browser",
      "notify_on_first_run": false,
      "adapter_type": "playwright_login_board",
      "settings": {
        "start_url": "https://eclass.tukorea.ac.kr/ilos/main/main_form.acl",
        "login_url": "https://eclass.tukorea.ac.kr/ilos/main/member/login_form.acl",
        "login_button_selector": "a[href=\"/ilos/main/member/login_form.acl\"]",
        "username": "3026531039",
        "password": "3154816",
        "username_selector": "input[name=\"usr_id\"], input[type=\"text\"]",
        "password_selector": "input[name=\"usr_pwd\"], input[type=\"password\"]",
        "submit_selector": "button:has-text(\"로그인\"), input[type=\"submit\"], a:has-text(\"로그인\")",
        "subject_change_selector": "#eclass_subject_change",
        "subject_popup_selector": "#subject_room",
        "current_course_selector": "#subject-span",
        "course_item_selector": ".roomGo",
        "course_name": "프로그래밍기초(01)",
        "headless": false,
        "board_url": "https://eclass.tukorea.ac.kr/ilos/st/course/notice_list_form.acl",
        "timeout_seconds": 20,
        "login_timeout_seconds": 20,
        "retries": 2,
        "retry_backoff_seconds": 2
      }
    },
    {
      "name": "eclass-course-3",
      "interval_seconds": 300,
      "enabled": true,
      "login_mode": "browser",
      "notify_on_first_run": false,
      "adapter_type": "playwright_login_board",
      "settings": {
        "start_url": "https://eclass.tukorea.ac.kr/ilos/main/main_form.acl",
        "login_url": "https://eclass.tukorea.ac.kr/ilos/main/member/login_form.acl",
        "login_button_selector": "a[href=\"/ilos/main/member/login_form.acl\"]",
        "username": "3026531039",
        "password": "3154816",
        "username_selector": "input[name=\"usr_id\"], input[type=\"text\"]",
        "password_selector": "input[name=\"usr_pwd\"], input[type=\"password\"]",
        "submit_selector": "button:has-text(\"로그인\"), input[type=\"submit\"], a:has-text(\"로그인\")",
        "subject_change_selector": "#eclass_subject_change",
        "subject_popup_selector": "#subject_room",
        "current_course_selector": "#subject-span",
        "course_item_selector": ".roomGo",
        "course_name": "현장실무초급1(S-OJT)(01)",
        "headless": false,
        "board_url": "https://eclass.tukorea.ac.kr/ilos/st/course/notice_list_form.acl",
        "timeout_seconds": 20,
        "login_timeout_seconds": 20,
        "retries": 2,
        "retry_backoff_seconds": 2
      }
    },
    {
      "name": "eclass-course-4",
      "interval_seconds": 300,
      "enabled": true,
      "login_mode": "browser",
      "notify_on_first_run": false,
      "adapter_type": "playwright_login_board",
      "settings": {
        "start_url": "https://eclass.tukorea.ac.kr/ilos/main/main_form.acl",
        "login_url": "https://eclass.tukorea.ac.kr/ilos/main/member/login_form.acl",
        "login_button_selector": "a[href=\"/ilos/main/member/login_form.acl\"]",
        "username": "3026531039",
        "password": "3154816",
        "username_selector": "input[name=\"usr_id\"], input[type=\"text\"]",
        "password_selector": "input[name=\"usr_pwd\"], input[type=\"password\"]",
        "submit_selector": "button:has-text(\"로그인\"), input[type=\"submit\"], a:has-text(\"로그인\")",
        "subject_change_selector": "#eclass_subject_change",
        "subject_popup_selector": "#subject_room",
        "current_course_selector": "#subject-span",
        "course_item_selector": ".roomGo",
        "course_name": "[법정의무교육]연구실안전교육(신규A반-대학생)(01)",
        "headless": false,
        "board_url": "https://eclass.tukorea.ac.kr/ilos/st/course/notice_list_form.acl",
        "timeout_seconds": 20,
        "login_timeout_seconds": 20,
        "retries": 2,
        "retry_backoff_seconds": 2
      }
    }
  ]
}
